parasnake/__init__.py
parasnake/ps_config.py
parasnake/ps_message.py
parasnake/ps_node.py
parasnake/ps_nodeid.py
parasnake/ps_server.py
parasnake/py.typed
parasnake-0.1.dist-info/METADATA
parasnake-0.1.dist-info/WHEEL
parasnake-0.1.dist-info/licenses/LICENSE
parasnake-0.1.dist-info/RECORD
