Metadata-Version: 2.4
Name: Parasnake
Version: 0.1
Summary: Distributed number crunching with Python.
Project-URL: Repository, https://github.com/willi-kappler/parasnake
Author-email: Willi Kappler <grandor@gmx.de>
Maintainer-email: Willi Kappler <grandor@gmx.de>
License-Expression: MIT
License-File: LICENSE
Keywords: computing,distributed,network,numeric,simulation
Classifier: License :: OSI Approved :: MIT License
Classifier: Programming Language :: Python :: 3.12
Requires-Python: >=3.12
Requires-Dist: cryptography>=42.0.0
